Metadata-Version: 2.1
Name: ExcelExtractorJsonPDF
Version: 0.1
Summary: Python package for converting data from Excel to JSON and PDF
Home-page: https://github.com/IvanGael/ExcelExtractorJsonPDF
Author: Ivan APEDO
Author-email: apedoivan@gmail.com
License: MIT
Platform: UNKNOWN
License-File: LICENSE.md
